pyBackup-0.0.4.dist-info/DESCRIPTION.rst
pyBackup-0.0.4.dist-info/METADATA
pyBackup-0.0.4.dist-info/RECORD
pyBackup-0.0.4.dist-info/WHEEL
pyBackup-0.0.4.dist-info/metadata.json
pyBackup-0.0.4.dist-info/top_level.txt
pybackup/__init__.py
pybackup/backup.py
pybackup/settings.py
pybackup/utils.py
