Metadata-Version: 2.0
Name: pyBackup
Version: 0.0.4
Summary: Python module for Backup routinesof files and folders
Home-page: https://github.com/FRReinert/PyBackup
Author: Fabricio Roberto reinert
Author-email: fabricio.reinert@live.com
License: MIT license
Keywords: Python,backup,files,folders
Platform: UNKNOWN
Classifier: Development Status :: 2 - Pre-Alpha
Classifier: Intended Audience :: Developers
Classifier: License :: OSI Approved :: MIT License
Classifier: Natural Language :: English
Classifier: Programming Language :: Python :: 3.6
